{
  "id": "ng-waec-biology-ss1",
  "country": "Nigeria",
  "curriculum": "WAEC",
  "level": "Senior High School",
  "class": "Class 1",
  "subject": "Biology",
  "terms": [
    {
      "id": "term1",
      "name": "First Term",
      "theme": "Organization of Life",
      "topics": [
        {
          "order": 1,
          "title": "Recognizing Living Things",
          "slug": "recognizing-living-things"
        },
        {
          "order": 2,
          "title": "Classification of Living Things",
          "slug": "classification-of-living-things",
          "subtopics": [
            "Monera",
            "Protista",
            "Fungi",
            "Plantae",
            "Animalia"
          ]
        },
        {
          "order": 3,
          "title": "The Cell",
          "slug": "the-cell"
        },
        {
          "order": 4,
          "title": "The Cell and its Environment",
          "slug": "the-cell-and-its-environment"
        },
        {
          "order": 5,
          "title": "Properties and Functions of the Cell",
          "slug": "properties-and-functions-of-the-cell"
        },
        {
          "order": 6,
          "title": "Tissues and Supporting Systems",
          "slug": "tissues-and-supporting-systems"
        },
        {
          "order": 7,
          "title": "Nutrition in Animals",
          "slug": "nutrition-in-animals"
        }
      ]
    },
    {
      "id": "term2",
      "name": "Second Term",
      "theme": "The Organism and Its Environment",
      "topics": [
        {
          "order": 1,
          "title": "Basic Ecological Concepts",
          "slug": "basic-ecological-concepts"
        },
        {
          "order": 2,
          "title": "Functioning Ecosystem",
          "slug": "functioning-ecosystem",
          "subtopics": [
            "Autotrophy",
            "Heterotrophy",
            "Food Webs",
            "Trophic Levels"
          ]
        },
        {
          "order": 3,
          "title": "Energy Transformation in Nature",
          "slug": "energy-transformation-in-nature"
        },
        {
          "order": 4,
          "title": "Relevance of Biology to Agriculture",
          "slug": "relevance-of-biology-to-agriculture"
        },
        {
          "order": 5,
          "title": "Micro-organisms Around Us",
          "slug": "micro-organisms-around-us"
        },
        {
          "order": 6,
          "title": "Micro-organisms in Action",
          "slug": "micro-organisms-in-action"
        },
        {
          "order": 7,
          "title": "Micro-organisms and Better Health",
          "slug": "micro-organisms-and-better-health"
        },
        {
          "order": 8,
          "title": "Marine Habitat",
          "slug": "marine-habitat"
        },
        {
          "order": 9,
          "title": "Estuarine Habitat",
          "slug": "estuarine-habitat"
        }
      ]
    },
    {
      "id": "term3",
      "name": "Third Term",
      "theme": "The Organism and Its Environment / Continuity of Life",
      "topics": [
        {
          "order": 1,
          "title": "Fresh Water Habitat",
          "slug": "fresh-water-habitat"
        },
        {
          "order": 2,
          "title": "Marsh Habitat",
          "slug": "marsh-habitat"
        },
        {
          "order": 3,
          "title": "Forest Habitat",
          "slug": "forest-habitat"
        },
        {
          "order": 4,
          "title": "Grassland Habitat",
          "slug": "grassland-habitat"
        },
        {
          "order": 5,
          "title": "Arid Land Habitat",
          "slug": "arid-land-habitat"
        },
        {
          "order": 6,
          "title": "Reproduction in Unicellular Organisms and Invertebrates",
          "slug": "reproduction-in-unicellular-organisms-and-invertebrates"
        }
      ]
    }
  ]
}
